MANIFEST.in
README.txt
requirements.txt
setup.py
pymdtoc/__init__.py
pymdtoc/cli.py
pymdtoc.egg-info/PKG-INFO
pymdtoc.egg-info/SOURCES.txt
pymdtoc.egg-info/dependency_links.txt
pymdtoc.egg-info/entry_points.txt
pymdtoc.egg-info/requires.txt
pymdtoc.egg-info/top_level.txt