Metadata-Version: 1.1
Name: pymdtoc
Version: 1.0
Summary: Add table of contents to markdown files
Home-page: https://github.com/cyriac/pymdtoc
Author: cyriac
Author-email: me@cyriacthomas.com
License: MIT
Download-URL: https://github.com/cyriac/pymdtoc/archive/v1.0.tar.gz
Keywords: markdown,toc,md
Platform: UNKNOWN
